[
    {
        "expansionId": "mobile_photo_basics",
        "patchOrder": "1",
        "sortOrder": "1",
        "contentType": "guide",
        "title": "Mobile Photo Basics",
        "packageName": "org.storymaker.app",
        "description": "Learn to make compelling photographs",
        "thumbnailPath": "images/content_packs/mobile_photo_basics_cover.png",
        "expansionFilePath": "Android/data/org.storymaker.app/files/",
        "expansionFileUrl": "https://s3-us-west-1.amazonaws.com/storymakerorg/appdata/obb/org.storymaker.app/",
        "expansionFileVersion": "20"
    },
    {
        "expansionId": "g_odvw",
        "patchOrder": "2",
        "sortOrder": "2",
        "contentType": "guide",
        "title": "Learn to Make Better Video",
        "packageName": "org.storymaker.app",
        "description": "A one day workshop in video basics",
        "thumbnailPath": "images/content_packs/g_odvw_cover.png",
        "expansionFilePath": "Android/data/org.storymaker.app/files/",
        "expansionFileUrl": "https://s3-us-west-1.amazonaws.com/storymakerorg/appdata/obb/org.storymaker.app/",
        "expansionFileVersion": "20"
    },
    {
        "expansionId": "default",
        "patchOrder": "3",
        "sortOrder": "3",
        "contentType": "guide",
        "title": "Story Assistant",
        "packageName": "org.storymaker.app",
        "description": "Answer a few questions to get a story template",
        "thumbnailPath": "images/content_packs/default_cover.png",
        "expansionFilePath": "Android/data/org.storymaker.app/files/",
        "expansionFileUrl": "https://s3-us-west-1.amazonaws.com/storymakerorg/appdata/obb/org.storymaker.app/",
        "expansionFileVersion": "20"
    },
    {
        "expansionId": "learning_guide",
        "patchOrder": "4",
        "sortOrder": "4",
        "contentType": "guide",
        "title": "Basic Elements of a Story",
        "packageName": "org.storymaker.app",
        "description": "Three steps to stronger stories",
        "thumbnailPath": "images/content_packs/learning_guide_cover.jpg",
        "expansionFilePath": "Android/data/org.storymaker.app/files/",
        "expansionFileUrl": "https://s3-us-west-1.amazonaws.com/storymakerorg/appdata/obb/org.storymaker.app/",
        "expansionFileVersion": "20"
    },
    {
        "expansionId": "g_welcome",
        "patchOrder": "5",
        "sortOrder": "5",
        "contentType": "guide",
        "title": "Welcome to StoryMaker",
        "packageName": "org.storymaker.app",
        "description": "Tour through StoryMaker's features",
        "thumbnailPath": "images/content_packs/g_welcome_cover.jpg",
        "expansionFilePath": "Android/data/org.storymaker.app/files/",
        "expansionFileUrl": "https://s3-us-west-1.amazonaws.com/storymakerorg/appdata/obb/org.storymaker.app/",
        "expansionFileVersion": "20"
    },
    
    
    
    {
        "expansionId": "journalism_part_1-mena",
        "patchOrder": "6",
        "sortOrder": "6",
        "contentType": "lesson",
        "title": "Journalism 1 - MENA Edition",
        "packageName": "org.storymaker.app",
        "description": "Social Media Basics and 4 more lessons",
        "thumbnailPath": "images/content_packs/journalism_part_1_mena_cover.png",
        "expansionFilePath": "Android/data/org.storymaker.app/files/",
        "expansionFileUrl": "https://s3-us-west-1.amazonaws.com/storymakerorg/appdata/obb/org.storymaker.app/",
        "expansionFileVersion": "20"
    },
    {
        "expansionId": "journalism_part_1-persian",
        "patchOrder": "7",
        "sortOrder": "7",
        "contentType": "lesson",
        "title": "Journalism 1 - Persian Edition",
        "packageName": "org.storymaker.app",
        "description": "Social Media Basics and 4 more lessons",
        "thumbnailPath": "images/content_packs/journalism_part_1_persian_cover.png",
        "expansionFilePath": "Android/data/org.storymaker.app/files/",
        "expansionFileUrl": "https://s3-us-west-1.amazonaws.com/storymakerorg/appdata/obb/org.storymaker.app/",
        "expansionFileVersion": "20"
    },
    {
        "expansionId": "journalism_part_1-burundi",
        "patchOrder": "8",
        "sortOrder": "8",
        "contentType": "lesson",
        "title": "Journalism 1 - Burundi Edition",
        "packageName": "org.storymaker.app",
        "description": "Social Media Basics and 4 more lessons",
        "thumbnailPath": "images/content_packs/journalism_part_1_burundi_cover.png",
        "expansionFilePath": "Android/data/org.storymaker.app/files/",
        "expansionFileUrl": "https://s3-us-west-1.amazonaws.com/storymakerorg/appdata/obb/org.storymaker.app/",
        "expansionFileVersion": "20"
    },
    {
        "expansionId": "journalism_part_2-mena",
        "patchOrder": "9",
        "sortOrder": "9",
        "contentType": "lesson",
        "title": "Journalism 2 - MENA Edition",
        "packageName": "org.storymaker.app",
        "description": "Evolution of a Story and 3 more lessons",
        "thumbnailPath": "images/content_packs/journalism_part_2_mena_cover.png",
        "expansionFilePath": "Android/data/org.storymaker.app/files/",
        "expansionFileUrl": "https://s3-us-west-1.amazonaws.com/storymakerorg/appdata/obb/org.storymaker.app/",
        "expansionFileVersion": "20"
    },
    {
        "expansionId": "journalism_part_2-persian",
        "patchOrder": "10",
        "sortOrder": "10",
        "contentType": "lesson",
        "title": "Journalism 2 - Persian Edition",
        "packageName": "org.storymaker.app",
        "description": "Evolution of a Story and 3 more lessons",
        "thumbnailPath": "images/content_packs/journalism_part_2_persian_cover.png",
        "expansionFilePath": "Android/data/org.storymaker.app/files/",
        "expansionFileUrl": "https://s3-us-west-1.amazonaws.com/storymakerorg/appdata/obb/org.storymaker.app/",
        "expansionFileVersion": "20"
    },
    {
        "expansionId": "journalism_part_2-burundi",
        "patchOrder": "11",
        "sortOrder": "11",
        "contentType": "lesson",
        "title": "Journalism 2 - Burundi Edition",
        "packageName": "org.storymaker.app",
        "description": "Evolution of a Story and 3 more lessons",
        "thumbnailPath": "images/content_packs/journalism_part_2_burundi_cover.png",
        "expansionFilePath": "Android/data/org.storymaker.app/files/",
        "expansionFileUrl": "https://s3-us-west-1.amazonaws.com/storymakerorg/appdata/obb/org.storymaker.app/",
        "expansionFileVersion": "20"
    },
    
    {
        "expansionId": "security-mena",
        "patchOrder": "12",
        "sortOrder": "12",
        "contentType": "lesson",
        "title": "Security - MENA Edition",
        "packageName": "org.storymaker.app",
        "description": "How can I use SMS Safely and 6 more lessons",
        "thumbnailPath": "images/content_packs/security_mena_cover.png",
        "expansionFilePath": "Android/data/org.storymaker.app/files/",
        "expansionFileUrl": "https://s3-us-west-1.amazonaws.com/storymakerorg/appdata/obb/org.storymaker.app/",
        "expansionFileVersion": "20"
    },
    {
        "expansionId": "security-persian",
        "patchOrder": "13",
        "sortOrder": "13",
        "contentType": "lesson",
        "title": "Security - Persian Edition",
        "packageName": "org.storymaker.app",
        "description": "How can I use SMS Safely and 6 more lessons",
        "thumbnailPath": "images/content_packs/security_persian_cover.png",
        "expansionFilePath": "Android/data/org.storymaker.app/files/",
        "expansionFileUrl": "https://s3-us-west-1.amazonaws.com/storymakerorg/appdata/obb/org.storymaker.app/",
        "expansionFileVersion": "20"
    },
    {
        "expansionId": "security-burundi",
        "patchOrder": "14",
        "sortOrder": "14",
        "contentType": "lesson",
        "title": "Security - Burundi Edition",
        "packageName": "org.storymaker.app",
        "description": "How can I use SMS Safely and 6 more lessons",
        "thumbnailPath": "images/content_packs/security_burundi_cover.png",
        "expansionFilePath": "Android/data/org.storymaker.app/files/",
        "expansionFileUrl": "https://s3-us-west-1.amazonaws.com/storymakerorg/appdata/obb/org.storymaker.app/",
        "expansionFileVersion": "20"
    },
    
    {
        "expansionId": "audio-mena",
        "patchOrder": "15",
        "sortOrder": "15",
        "contentType": "lesson",
        "title": "Audio - MENA Edition",
        "packageName": "org.storymaker.app",
        "description": "Audio Basics and 5 more lessons",
        "thumbnailPath": "images/content_packs/audio_mena_cover.png",
        "expansionFilePath": "Android/data/org.storymaker.app/files/",
        "expansionFileUrl": "https://s3-us-west-1.amazonaws.com/storymakerorg/appdata/obb/org.storymaker.app/",
        "expansionFileVersion": "20"
    },
    {
        "expansionId": "audio-persian",
        "patchOrder": "16",
        "sortOrder": "16",
        "contentType": "lesson",
        "title": "Audio - Persian Edition",
        "packageName": "org.storymaker.app",
        "description": "Audio Basics and 5 more lessons",
        "thumbnailPath": "images/content_packs/audio_persian_cover.png",
        "expansionFilePath": "Android/data/org.storymaker.app/files/",
        "expansionFileUrl": "https://s3-us-west-1.amazonaws.com/storymakerorg/appdata/obb/org.storymaker.app/",
        "expansionFileVersion": "20"
    },
    {
        "expansionId": "audio-burundi",
        "patchOrder": "20",
        "sortOrder": "20",
        "contentType": "lesson",
        "title": "Audio - Burundi Edition",
        "packageName": "org.storymaker.app",
        "description": "Audio Basics and 5 more lessons",
        "thumbnailPath": "images/content_packs/audio_burundi_cover.png",
        "expansionFilePath": "Android/data/org.storymaker.app/files/",
        "expansionFileUrl": "https://s3-us-west-1.amazonaws.com/storymakerorg/appdata/obb/org.storymaker.app/",
        "expansionFileVersion": "20"
    },
    
    {
        "expansionId": "photography_1-mena",
        "patchOrder": "20",
        "sortOrder": "20",
        "contentType": "lesson",
        "title": "Photography 1 - MENA Edition",
        "packageName": "org.storymaker.app",
        "description": "Camera Basics and 5 more lessons",
        "thumbnailPath": "images/content_packs/photography_1_mena_cover.png",
        "expansionFilePath": "Android/data/org.storymaker.app/files/",
        "expansionFileUrl": "https://s3-us-west-1.amazonaws.com/storymakerorg/appdata/obb/org.storymaker.app/",
        "expansionFileVersion": "20"
    },
    {
        "expansionId": "photography_1-persian",
        "patchOrder": "20",
        "sortOrder": "20",
        "contentType": "lesson",
        "title": "Photography 1 - Persian Edition",
        "packageName": "org.storymaker.app",
        "description": "Camera Basics and 5 more lessons",
        "thumbnailPath": "images/content_packs/photography_1_persian_cover.png",
        "expansionFilePath": "Android/data/org.storymaker.app/files/",
        "expansionFileUrl": "https://s3-us-west-1.amazonaws.com/storymakerorg/appdata/obb/org.storymaker.app/",
        "expansionFileVersion": "20"
    },
    {
        "expansionId": "photography_1-burundi",
        "patchOrder": "20",
        "sortOrder": "20",
        "contentType": "lesson",
        "title": "Photography 1 - Burundi Edition",
        "packageName": "org.storymaker.app",
        "description": "Camera Basics and 5 more lessons",
        "thumbnailPath": "images/content_packs/photography_1_burundi_cover.png",
        "expansionFilePath": "Android/data/org.storymaker.app/files/",
        "expansionFileUrl": "https://s3-us-west-1.amazonaws.com/storymakerorg/appdata/obb/org.storymaker.app/",
        "expansionFileVersion": "20"
    },
    
    {
        "expansionId": "photography_2-mena",
        "patchOrder": "21",
        "sortOrder": "21",
        "contentType": "lesson",
        "title": "Photography 2 - MENA Edition",
        "packageName": "org.storymaker.app",
        "description": "The Photo Essay and 4 more lessons",
        "thumbnailPath": "images/content_packs/photography_2_mena_cover.png",
        "expansionFilePath": "Android/data/org.storymaker.app/files/",
        "expansionFileUrl": "https://s3-us-west-1.amazonaws.com/storymakerorg/appdata/obb/org.storymaker.app/",
        "expansionFileVersion": "20"
    },
    {
        "expansionId": "photography_2-persian",
        "patchOrder": "22",
        "sortOrder": "22",
        "contentType": "lesson",
        "title": "Photography 2 - Persian Edition",
        "packageName": "org.storymaker.app",
        "description": "The Photo Essay and 4 more lessons",
        "thumbnailPath": "images/content_packs/photography_2_persian_cover.png",
        "expansionFilePath": "Android/data/org.storymaker.app/files/",
        "expansionFileUrl": "https://s3-us-west-1.amazonaws.com/storymakerorg/appdata/obb/org.storymaker.app/",
        "expansionFileVersion": "20"
    },
    {
        "expansionId": "photography_2-burundi",
        "patchOrder": "23",
        "sortOrder": "23",
        "contentType": "lesson",
        "title": "Photography 2 - Burundi Edition",
        "packageName": "org.storymaker.app",
        "description": "The Photo Essay and 4 more lessons",
        "thumbnailPath": "images/content_packs/photography_2_burundi_cover.png",
        "expansionFilePath": "Android/data/org.storymaker.app/files/",
        "expansionFileUrl": "https://s3-us-west-1.amazonaws.com/storymakerorg/appdata/obb/org.storymaker.app/",
        "expansionFileVersion": "20"
    },
    
    {
        "expansionId": "video_1-mena",
        "patchOrder": "24",
        "sortOrder": "24",
        "contentType": "lesson",
        "title": "Video 1 - MENA Edition",
        "packageName": "org.storymaker.app",
        "description": "Video Basics and 3 more lessons",
        "thumbnailPath": "images/content_packs/video_1_mena_cover.png",
        "expansionFilePath": "Android/data/org.storymaker.app/files/",
        "expansionFileUrl": "https://s3-us-west-1.amazonaws.com/storymakerorg/appdata/obb/org.storymaker.app/",
        "expansionFileVersion": "20"
    },
    {
        "expansionId": "video_1-persian",
        "patchOrder": "25",
        "sortOrder": "25",
        "contentType": "lesson",
        "title": "Video 1 - Persian Edition",
        "packageName": "org.storymaker.app",
        "description": "Video Basics and 3 more lessons",
        "thumbnailPath": "images/content_packs/video_1_persian_cover.png",
        "expansionFilePath": "Android/data/org.storymaker.app/files/",
        "expansionFileUrl": "https://s3-us-west-1.amazonaws.com/storymakerorg/appdata/obb/org.storymaker.app/",
        "expansionFileVersion": "20"
    },
    {
        "expansionId": "video_1-burundi",
        "patchOrder": "26",
        "sortOrder": "26",
        "contentType": "lesson",
        "title": "Video 1 - Burundi Edition",
        "packageName": "org.storymaker.app",
        "description": "Video Basics and 3 more lessons",
        "thumbnailPath": "images/content_packs/video_1_burundi_cover.png",
        "expansionFilePath": "Android/data/org.storymaker.app/files/",
        "expansionFileUrl": "https://s3-us-west-1.amazonaws.com/storymakerorg/appdata/obb/org.storymaker.app/",
        "expansionFileVersion": "20"
    },
    
    {
        "expansionId": "video_2-mena",
        "patchOrder": "27",
        "sortOrder": "27",
        "contentType": "lesson",
        "title": "Video 2 - MENA Edition",
        "packageName": "org.storymaker.app",
        "description": "Framing your Shot and 4 more lessons",
        "thumbnailPath": "images/content_packs/video_2_mena_cover.png",
        "expansionFilePath": "Android/data/org.storymaker.app/files/",
        "expansionFileUrl": "https://s3-us-west-1.amazonaws.com/storymakerorg/appdata/obb/org.storymaker.app/",
        "expansionFileVersion": "20"
    },
    {
        "expansionId": "video_2-persian",
        "patchOrder": "28",
        "sortOrder": "28",
        "contentType": "lesson",
        "title": "Video 2 - Persian Edition",
        "packageName": "org.storymaker.app",
        "description": "Framing your Shot and 4 more lessons",
        "thumbnailPath": "images/content_packs/video_2_persian_cover.png",
        "expansionFilePath": "Android/data/org.storymaker.app/files/",
        "expansionFileUrl": "https://s3-us-west-1.amazonaws.com/storymakerorg/appdata/obb/org.storymaker.app/",
        "expansionFileVersion": "20"
    },
    {
        "expansionId": "video_2-burundi",
        "patchOrder": "29",
        "sortOrder": "29",
        "contentType": "lesson",
        "title": "Video 2 - Burundi Edition",
        "packageName": "org.storymaker.app",
        "description": "Framing your Shot and 4 more lessons",
        "thumbnailPath": "images/content_packs/video_2_burundi_cover.png",
        "expansionFilePath": "Android/data/org.storymaker.app/files/",
        "expansionFileUrl": "https://s3-us-west-1.amazonaws.com/storymakerorg/appdata/obb/org.storymaker.app/",
        "expansionFileVersion": "20"
    },
    
    {
        "expansionId": "story-mena",
        "patchOrder": "30",
        "sortOrder": "30",
        "contentType": "lesson",
        "title": "Story - MENA Edition",
        "packageName": "org.storymaker.app",
        "description": "Central Question and 6 more lessons",
        "thumbnailPath": "images/content_packs/story_mena_cover.png",
        "expansionFilePath": "Android/data/org.storymaker.app/files/",
        "expansionFileUrl": "https://s3-us-west-1.amazonaws.com/storymakerorg/appdata/obb/org.storymaker.app/",
        "expansionFileVersion": "20"
    },
    {
        "expansionId": "story-persian",
        "patchOrder": "31",
        "sortOrder": "31",
        "contentType": "lesson",
        "title": "Story - Persian Edition",
        "packageName": "org.storymaker.app",
        "description": "Central Question and 6 more lessons",
        "thumbnailPath": "images/content_packs/story_persian_cover.png",
        "expansionFilePath": "Android/data/org.storymaker.app/files/",
        "expansionFileUrl": "https://s3-us-west-1.amazonaws.com/storymakerorg/appdata/obb/org.storymaker.app/",
        "expansionFileVersion": "20"
    },
    {
        "expansionId": "story-burundi",
        "patchOrder": "32",
        "sortOrder": "32",
        "contentType": "lesson",
        "title": "Story - Burundi Edition",
        "packageName": "org.storymaker.app",
        "description": "Central Question and 6 more lessons",
        "thumbnailPath": "images/content_packs/story_burundi_cover.png",
        "expansionFilePath": "Android/data/org.storymaker.app/files/",
        "expansionFileUrl": "https://s3-us-west-1.amazonaws.com/storymakerorg/appdata/obb/org.storymaker.app/",
        "expansionFileVersion": "20"
    },
    
    
    
    
    
    {
        "expansionId": "t_video",
        "patchOrder": "33",
        "sortOrder": "33",
        "contentType": "template",
        "title": "Make a Video Story",
        "packageName": "org.storymaker.app",
        "description": "7 templates for video stories",
        "thumbnailPath": "images/content_packs/t_video_cover.png",
        "expansionFilePath": "Android/data/org.storymaker.app/files/",
        "expansionFileUrl": "https://s3-us-west-1.amazonaws.com/storymakerorg/appdata/obb/org.storymaker.app/",
        "expansionFileVersion": "20"
    },
    {
        "expansionId": "t_audio",
        "patchOrder": "34",
        "sortOrder": "34",
        "contentType": "template",
        "title": "Make an Audio Story",
        "packageName": "org.storymaker.app",
        "description": "Record an audio story in a variety of ways",
        "thumbnailPath": "images/content_packs/t_audio_cover.png",
        "expansionFilePath": "Android/data/org.storymaker.app/files/",
        "expansionFileUrl": "https://s3-us-west-1.amazonaws.com/storymakerorg/appdata/obb/org.storymaker.app/",
        "expansionFileVersion": "20"
    },
    {
        "expansionId": "t_photo",
        "patchOrder": "35",
        "sortOrder": "35",
        "contentType": "template",
        "title": "Make Photo Essay Stories",
        "packageName": "org.storymaker.app",
        "description": "Tell a story with several photos",
        "thumbnailPath": "images/content_packs/t_photo_cover.png",
        "expansionFilePath": "Android/data/org.storymaker.app/files/",
        "expansionFileUrl": "https://s3-us-west-1.amazonaws.com/storymakerorg/appdata/obb/org.storymaker.app/",
        "expansionFileVersion": "20"
    },
    {
        "expansionId": "t_news",
        "patchOrder": "36",
        "sortOrder": "36",
        "contentType": "template",
        "title": "Make a News Report Story",
        "packageName": "org.storymaker.app",
        "description": "News stories on different topics",
        "thumbnailPath": "images/content_packs/t_news_cover.png",
        "expansionFilePath": "Android/data/org.storymaker.app/files/",
        "expansionFileUrl": "https://s3-us-west-1.amazonaws.com/storymakerorg/appdata/obb/org.storymaker.app/",
        "expansionFileVersion": "20"
    },
    {
        "expansionId": "t_process",
        "patchOrder": "37",
        "sortOrder": "37",
        "contentType": "template",
        "title": "Make a Story Based on a Process",
        "packageName": "org.storymaker.app",
        "description": "Tell a story using a single process",
        "thumbnailPath": "images/content_packs/t_process_cover.png",
        "expansionFilePath": "Android/data/org.storymaker.app/files/",
        "expansionFileUrl": "https://s3-us-west-1.amazonaws.com/storymakerorg/appdata/obb/org.storymaker.app/",
        "expansionFileVersion": "20"
    },
    {
        "expansionId": "t_citizen_journalist",
        "patchOrder": "38",
        "sortOrder": "38",
        "contentType": "template",
        "title": "Citizen Journalism Pack",
        "packageName": "org.storymaker.app",
        "description": "Begin telling stories you care about",
        "thumbnailPath": "images/content_packs/t_citizen_journalist_cover.jpg",
        "expansionFilePath": "Android/data/org.storymaker.app/files/",
        "expansionFileUrl": "https://s3-us-west-1.amazonaws.com/storymakerorg/appdata/obb/org.storymaker.app/",
        "expansionFileVersion": "20"
    },
    {
        "expansionId": "t_ukraine_school_cj",
        "patchOrder": "39",
        "sortOrder": "39",
        "contentType": "template",
        "title": "Ukrainian Pack",
        "packageName": "org.storymaker.app",
        "description": "Ukranian news stories",
        "thumbnailPath": "images/content_packs/t_ukraine_school_cj_cover.jpg",
        "expansionFilePath": "Android/data/org.storymaker.app/files/",
        "expansionFileUrl": "https://s3-us-west-1.amazonaws.com/storymakerorg/appdata/obb/org.storymaker.app/",
        "expansionFileVersion": "20"
    },
    {
        "expansionId": "journalism_part_1-ethiopia",
        "patchOrder": "40",
        "sortOrder": "40",
        "contentType": "lesson",
        "title": "Journalism 1 - Ethiopia Edition",
        "packageName": "org.storymaker.app",
        "description": "Social Media Basics and 4 more lessons",
        "thumbnailPath": "images/content_packs/journalism_part_1_ethiopia_cover.png",
        "expansionFilePath": "Android/data/org.storymaker.app/files/",
        "expansionFileUrl": "https://s3-us-west-1.amazonaws.com/storymakerorg/appdata/obb/org.storymaker.app/",
        "expansionFileVersion": "20"
    },
    {
        "expansionId": "journalism_part_2-ethiopia",
        "patchOrder": "41",
        "sortOrder": "41",
        "contentType": "lesson",
        "title": "Journalism 2 - Ethiopia Edition",
        "packageName": "org.storymaker.app",
        "description": "Evolution of a Story and 3 more lessons",
        "thumbnailPath": "images/content_packs/journalism_part_2_ethiopia_cover.png",
        "expansionFilePath": "Android/data/org.storymaker.app/files/",
        "expansionFileUrl": "https://s3-us-west-1.amazonaws.com/storymakerorg/appdata/obb/org.storymaker.app/",
        "expansionFileVersion": "20"
    },
    {
        "expansionId": "audio-ethiopia",
        "patchOrder": "42",
        "sortOrder": "42",
        "contentType": "lesson",
        "title": "Audio - Ethiopia Edition",
        "packageName": "org.storymaker.app",
        "description": "Audio Basics and 5 more lessons",
        "thumbnailPath": "images/content_packs/audio_ethiopia_cover.png",
        "expansionFilePath": "Android/data/org.storymaker.app/files/",
        "expansionFileUrl": "https://s3-us-west-1.amazonaws.com/storymakerorg/appdata/obb/org.storymaker.app/",
        "expansionFileVersion": "20"
    },
    {
        "expansionId": "photography_1-ethiopia",
        "patchOrder": "43",
        "sortOrder": "43",
        "contentType": "lesson",
        "title": "Photography 1 - Ethiopia Edition",
        "packageName": "org.storymaker.app",
        "description": "Camera Basics and 5 more lessons",
        "thumbnailPath": "images/content_packs/photography_1_ethiopia_cover.png",
        "expansionFilePath": "Android/data/org.storymaker.app/files/",
        "expansionFileUrl": "https://s3-us-west-1.amazonaws.com/storymakerorg/appdata/obb/org.storymaker.app/",
        "expansionFileVersion": "20"
    },
    {
        "expansionId": "photography_2-ethiopia",
        "patchOrder": "44",
        "sortOrder": "44",
        "contentType": "lesson",
        "title": "Photography 2 - Ethiopia Edition",
        "packageName": "org.storymaker.app",
        "description": "The Photo Essay and 4 more lessons",
        "thumbnailPath": "images/content_packs/photography_2_ethiopia_cover.png",
        "expansionFilePath": "Android/data/org.storymaker.app/files/",
        "expansionFileUrl": "https://s3-us-west-1.amazonaws.com/storymakerorg/appdata/obb/org.storymaker.app/",
        "expansionFileVersion": "20"
    },
    {
        "expansionId": "security-ethiopia",
        "patchOrder": "45",
        "sortOrder": "45",
        "contentType": "lesson",
        "title": "Security - Ethiopia Edition",
        "packageName": "org.storymaker.app",
        "description": "How can I use SMS Safely and 6 more lessons",
        "thumbnailPath": "images/content_packs/security_ethiopia_cover.png",
        "expansionFilePath": "Android/data/org.storymaker.app/files/",
        "expansionFileUrl": "https://s3-us-west-1.amazonaws.com/storymakerorg/appdata/obb/org.storymaker.app/",
        "expansionFileVersion": "20"
    },
    {
        "expansionId": "story-ethiopia",
        "patchOrder": "46",
        "sortOrder": "46",
        "contentType": "lesson",
        "title": "Story - Ethiopia Edition",
        "packageName": "org.storymaker.app",
        "description": "Central Question and 6 more lessons",
        "thumbnailPath": "images/content_packs/story_ethiopia_cover.png",
        "expansionFilePath": "Android/data/org.storymaker.app/files/",
        "expansionFileUrl": "https://s3-us-west-1.amazonaws.com/storymakerorg/appdata/obb/org.storymaker.app/",
        "expansionFileVersion": "20"
    },
    {
        "expansionId": "video_1-ethiopia",
        "patchOrder": "47",
        "sortOrder": "47",
        "contentType": "lesson",
        "title": "Video 1 - Ethiopia Edition",
        "packageName": "org.storymaker.app",
        "description": "Video Basics and 3 more lessons",
        "thumbnailPath": "images/content_packs/video_1_ethiopia_cover.png",
        "expansionFilePath": "Android/data/org.storymaker.app/files/",
        "expansionFileUrl": "https://s3-us-west-1.amazonaws.com/storymakerorg/appdata/obb/org.storymaker.app/",
        "expansionFileVersion": "20"
    },
    {
        "expansionId": "video_2-ethiopia",
        "patchOrder": "48",
        "sortOrder": "48",
        "contentType": "lesson",
        "title": "Video 2 - Ethiopia Edition",
        "packageName": "org.storymaker.app",
        "description": "Framing your Shot and 4 more lessons",
        "thumbnailPath": "images/content_packs/video_2_ethiopia_cover.png",
        "expansionFilePath": "Android/data/org.storymaker.app/files/",
        "expansionFileUrl": "https://s3-us-west-1.amazonaws.com/storymakerorg/appdata/obb/org.storymaker.app/",
        "expansionFileVersion": "20"
    }
]
